hvmnd_api_client/__init__.py
hvmnd_api_client/client.py
hvmnd_api_client-6.2.1.dist-info/METADATA
hvmnd_api_client-6.2.1.dist-info/WHEEL
hvmnd_api_client-6.2.1.dist-info/top_level.txt
hvmnd_api_client-6.2.1.dist-info/RECORD
