Metadata-Version: 2.4
Name: hvmnd_api_client
Version: 6.2.1
Summary: Python client library for the Go API application.
Home-page: https://github.com/Smarandii/hvmnd-api-client
Author: Smarandii
Author-email: olegsmarandi@gmail.com
Classifier: Programming Language :: Python :: 3
Classifier: Operating System :: OS Independent
Requires-Python: >=3.6
Requires-Dist: pytz>=2024.1
Requires-Dist: requests>=2.0.0
Provides-Extra: dev
Requires-Dist: pytest; extra == "dev"
Requires-Dist: python-dotenv; extra == "dev"
Dynamic: author
Dynamic: author-email
Dynamic: classifier
Dynamic: description
Dynamic: description-content-type
Dynamic: home-page
Dynamic: provides-extra
Dynamic: requires-dist
Dynamic: requires-python
Dynamic: summary
